prefer/__init__.py
prefer/configuration.py
prefer/configuration_spec.py
prefer/events.py
prefer/events_spec.py
prefer/loading.py
prefer/loading_spec.py
prefer/pathing.py
prefer/pathing_spec.py
prefer/formatters/__init__.py
prefer/formatters/defaults.py
prefer/formatters/formatter.py
prefer/formatters/formatter_spec.py
prefer/formatters/ini.py
prefer/formatters/ini_spec.py
prefer/formatters/json.py
prefer/formatters/json_spec.py
prefer/formatters/xml.py
prefer/formatters/xml_spec.py
prefer/formatters/yaml.py
prefer/formatters/yaml_spec.py
prefer/loaders/__init__.py
prefer/loaders/defaults.py
prefer/loaders/file.py
prefer/loaders/file_spec.py
prefer/loaders/loader.py
prefer/loaders/loader_spec.py
prefer-0.2.0.dist-info/METADATA
prefer-0.2.0.dist-info/WHEEL
prefer-0.2.0.dist-info/top_level.txt
prefer-0.2.0.dist-info/RECORD
