Metadata-Version: 2.4
Name: prefer
Version: 0.2.0
Summary: A user-preference focused configuration library for Python.
Author-email: LimpidTech <info@limpidtech.com>
License: MIT
Project-URL: Homepage, https://github.com/LimpidTech/prefer.py
Project-URL: Repository, https://github.com/LimpidTech/prefer.py
Project-URL: Issues, https://github.com/LimpidTech/prefer.py/issues
Classifier: Development Status :: 3 - Alpha
Classifier: Intended Audience :: Developers
Classifier: License :: OSI Approved :: MIT License
Classifier: Programming Language :: Python :: 3
Classifier: Programming Language :: Python :: 3.8
Classifier: Programming Language :: Python :: 3.9
Classifier: Programming Language :: Python :: 3.10
Classifier: Programming Language :: Python :: 3.11
Classifier: Programming Language :: Python :: 3.12
Requires-Python: >=3.8
Requires-Dist: PyYAML>=5.1
Requires-Dist: xmljson>=0.2.0
Requires-Dist: json5>=0.9.0
Provides-Extra: dev
Requires-Dist: pytest>=7.0; extra == "dev"
Requires-Dist: pytest-asyncio>=0.21.0; extra == "dev"
Requires-Dist: pytest-cov>=4.0; extra == "dev"
Requires-Dist: pytest-watch>=4.2; extra == "dev"
Requires-Dist: pytest-blockage>=0.2.0; extra == "dev"
Requires-Dist: mypy>=1.0; extra == "dev"
Requires-Dist: ruff>=0.1.0; extra == "dev"
Requires-Dist: mock>=4.0; extra == "dev"
Requires-Dist: types-PyYAML>=6.0; extra == "dev"
